poetry_asset_code/__init__.py
cdk_poetry_asset_code-0.1.0.dist-info/LICENSE
cdk_poetry_asset_code-0.1.0.dist-info/METADATA
cdk_poetry_asset_code-0.1.0.dist-info/WHEEL
cdk_poetry_asset_code-0.1.0.dist-info/RECORD
