Metadata-Version: 2.1
Name: cdk-poetry-asset-code
Version: 0.1.0
Summary: A custom AWS CDK construct that integrates Poetry for building Python Lambda function packages.
License: MIT
Author: TCL Research Europe
Author-email: tcl.research.eu@gmail.com
Requires-Python: >=3.12,<4.0
Classifier: License :: OSI Approved :: MIT License
Classifier: Programming Language :: Python :: 3
Classifier: Programming Language :: Python :: 3.12
Requires-Dist: aws-cdk-lib (>=2.130.0,<3.0.0)
Requires-Dist: constructs (>=10.3.0,<11.0.0)
